jaraco/classes/__init__.py
jaraco/classes/ancestry.py
jaraco/classes/meta.py
jaraco/classes/properties.py
jaraco/classes/py.typed
jaraco.classes-3.3.1.dist-info/LICENSE
jaraco.classes-3.3.1.dist-info/METADATA
jaraco.classes-3.3.1.dist-info/WHEEL
jaraco.classes-3.3.1.dist-info/top_level.txt
jaraco.classes-3.3.1.dist-info/RECORD
