Metadata-Version: 2.1
Name: jaraco.classes
Version: 3.3.1
Summary: Utility functions for Python class constructs
Home-page: https://github.com/jaraco/jaraco.classes
Author: Jason R. Coombs
Author-email: jaraco@jaraco.com
Classifier: Development Status :: 5 - Production/Stable
Classifier: Intended Audience :: Developers
Classifier: License :: OSI Approved :: MIT License
Classifier: Programming Language :: Python :: 3
Classifier: Programming Language :: Python :: 3 :: Only
Requires-Python: >=3.8
License-File: LICENSE
Requires-Dist: more_itertools
Provides-Extra: testing
Requires-Dist: pytest>=6; extra == "testing"
Requires-Dist: pytest-checkdocs>=2.4; extra == "testing"
Requires-Dist: pytest-cov; extra == "testing"
Requires-Dist: pytest-mypy; platform_python_implementation != "PyPy" and extra == "testing"
Requires-Dist: pytest-enabler>=2.2; extra == "testing"
Requires-Dist: pytest-ruff>=0.2.1; extra == "testing"
Provides-Extra: docs
Requires-Dist: sphinx>=3.5; extra == "docs"
Requires-Dist: sphinx<7.2.5; extra == "docs"
Requires-Dist: jaraco.packaging>=9.3; extra == "docs"
Requires-Dist: rst.linker>=1.9; extra == "docs"
Requires-Dist: furo; extra == "docs"
Requires-Dist: sphinx-lint; extra == "docs"
Requires-Dist: jaraco.tidelift>=1.4; extra == "docs"
